refkeeper/__init__.py
refkeeper-0.0.1.dist-info/METADATA
refkeeper-0.0.1.dist-info/WHEEL
refkeeper-0.0.1.dist-info/top_level.txt
refkeeper-0.0.1.dist-info/RECORD
